irys_sdk/__init__.py
irys_sdk/builder.py
irys_sdk/bundle/__init__.py
irys_sdk/bundle/constants.py
irys_sdk/bundle/create.py
irys_sdk/bundle/dataitem.py
irys_sdk/bundle/sign.py
irys_sdk/bundle/signers/__init__.py
irys_sdk/bundle/signers/ethereum.py
irys_sdk/bundle/signers/index.py
irys_sdk/bundle/signers/signer.py
irys_sdk/bundle/tags.py
irys_sdk/bundle/utils.py
irys_sdk/client.py
irys_sdk/fund.py
irys_sdk/tokens/__init__.py
irys_sdk/tokens/base.py
irys_sdk/tokens/ethereum.py
irys_sdk/types.py
irys_sdk/upload.py
irys_sdk/utils.py
irys_sdk-0.1.9.dist-info/METADATA
irys_sdk-0.1.9.dist-info/WHEEL
irys_sdk-0.1.9.dist-info/RECORD
