Metadata-Version: 2.1
Name: irys-sdk
Version: 0.1.9
Summary: Official python SDK for Irys bundlers
Home-page: https://github.com/Irys-xyz/python-sdk
License: MIT
Author: Jesse Wright
Author-email: jesse@irys.xyz
Requires-Python: >=3.10,<4.0
Classifier: License :: OSI Approved :: MIT License
Classifier: Programming Language :: Python :: 3
Classifier: Programming Language :: Python :: 3.10
Classifier: Programming Language :: Python :: 3.11
Classifier: Programming Language :: Python :: 3.12
Classifier: Programming Language :: Python :: 3.13
Requires-Dist: avro (>=1.12.0,<2.0.0)
Requires-Dist: base58 (>=2.1.1,<3.0.0)
Requires-Dist: eth-account (>=0.8.0,<0.9.0)
Requires-Dist: eth-keys (>=0.4.0,<0.5)
Requires-Dist: requests (==2.28.2)
Requires-Dist: setuptools (>=80.9.0,<81.0.0)
Requires-Dist: web3 (>=6.5.0,<7.0.0)
Project-URL: Repository, https://github.com/Irys-xyz/python-sdk
